pb_assistant/__init__.py
pb_assistant/pb_assistant.py
pb_assistant-1.0.1.dist-info/LICENSE
pb_assistant-1.0.1.dist-info/METADATA
pb_assistant-1.0.1.dist-info/WHEEL
pb_assistant-1.0.1.dist-info/top_level.txt
pb_assistant-1.0.1.dist-info/RECORD
