Metadata-Version: 2.1
Name: pb-assistant
Version: 1.0.1
Summary: A Python library to answer questions based on given data and additional queries using Gemini.
Home-page: https://github.com/FalconX80/pb_assistant
Author: Priyanshu Bhatt
Author-email: priyanshubhatt80@gmail.com
Classifier: Programming Language :: Python :: 3
Classifier: License :: OSI Approved :: MIT License
Classifier: Operating System :: OS Independent
Requires-Python: >=3.7
License-File: LICENSE
Requires-Dist: google-generativeai
